dglib/__init__.py
dglib/cache_util.py
dglib/csvex.py
dglib/dllexcludes.py
dglib/dotenv_util.py
dglib/excepthook.py
dglib/logutil.py
dglib/methrouter.py
dglib/runonce.py
dglib/souputil.py
dglib/thread_safe.py
dglib/tracer.py
dglib/txtutil.py
dglib/utils.py
dglib/xmlutil.py
dglib/basis/__init__.py
dglib/basis/dictxml.py
dglib/basis/ordered_dict.py
dglib/basis/pydicti.py
dglib/basis/singleton.py
dglib/basis/weakmethod.py
dglib/codec/__init__.py
dglib/codec/keyserial.py
dglib/config/SortableConfigParser.py
dglib/config/__init__.py
dglib/config/confutil.py
dglib/config/inifiles.py
dglib/db/__init__.py
dglib/db/db_utils.py
dglib/etc/__init__.py
dglib/etc/expired_checker.py
dglib/flask/__init__.py
dglib/flask/decorators.py
dglib/flask/util.py
dglib/network/__init__.py
dglib/network/bt_buffer.py
dglib/network/network.py
dglib/network/patch.py
dglib/network/sendmail.py
dglib/network/stringio_buffer.py
dglib/network/topicclient.py
dglib/network/topicserver.py
dglib/network/urlutil.py
dglib/network/wsgiserver.py
dglib/network/zmqutil.py
dglib/network/handler/__init__.py
dglib/network/handler/httphandler.py
dglib/ps/__init__.py
dglib/ps/conutil.py
dglib/ps/ps_utils.py
dglib/qt/QtEventName.py
dglib/qt/__init__.py
dglib/qt/qt4h.py
dglib/qt/qt_utils.py
dglib/qt/qt_utils2.py
dglib-0.4.7.dist-info/LICENSE
dglib-0.4.7.dist-info/METADATA
dglib-0.4.7.dist-info/WHEEL
dglib-0.4.7.dist-info/top_level.txt
dglib-0.4.7.dist-info/RECORD
