Metadata-Version: 2.1
Name: dglib
Version: 0.4.7
Summary: Daemon glance lib
Home-page: https://github.com/ddcatgg/dglib
Author: DDGG
Author-email: 990080@qq.com
License: UNKNOWN
Keywords: util,tool,ddgg
Platform: UNKNOWN
Classifier: Programming Language :: Python
Classifier: Programming Language :: Python :: 2.6
Classifier: Programming Language :: Python :: 2.7
Classifier: Development Status :: 4 - Beta
Classifier: Environment :: Other Environment
Classifier: Intended Audience :: Developers
Classifier: License :: OSI Approved :: MIT License
Classifier: Operating System :: Microsoft :: Windows
Classifier: Topic :: Software Development :: Libraries :: Python Modules
Classifier: Topic :: Utilities
